neuromeka_stereo/__init__.py
neuromeka_stereo/assets.py
neuromeka_stereo/fs_infer.py
neuromeka_stereo/realsense_demo.py
neuromeka_stereo/FoundationStereo_TRT/Utils.py
neuromeka_stereo/FoundationStereo_TRT/__init__.py
neuromeka_stereo/FoundationStereo_TRT/core/__init__.py
neuromeka_stereo/FoundationStereo_TRT/core/extractor.py
neuromeka_stereo/FoundationStereo_TRT/core/foundation_stereo.py
neuromeka_stereo/FoundationStereo_TRT/core/geometry.py
neuromeka_stereo/FoundationStereo_TRT/core/submodule.py
neuromeka_stereo/FoundationStereo_TRT/core/update.py
neuromeka_stereo/FoundationStereo_TRT/core/utils/__init__.py
neuromeka_stereo/FoundationStereo_TRT/core/utils/utils.py
neuromeka_stereo/FoundationStereo_TRT/depth_anything_pretrained_models/__init__.py
neuromeka_stereo/FoundationStereo_TRT/depth_anything_pretrained_models/blocks.py
neuromeka_stereo/FoundationStereo_TRT/depth_anything_pretrained_models/dpt.py
neuromeka_stereo/FoundationStereo_TRT/depth_anything_pretrained_models/util/__init__.py
neuromeka_stereo/FoundationStereo_TRT/depth_anything_pretrained_models/util/transform.py
neuromeka_stereo-0.1.2.dist-info/METADATA
neuromeka_stereo-0.1.2.dist-info/WHEEL
neuromeka_stereo-0.1.2.dist-info/entry_points.txt
neuromeka_stereo-0.1.2.dist-info/top_level.txt
neuromeka_stereo-0.1.2.dist-info/RECORD
