Metadata-Version: 2.4
Name: neuromeka_stereo
Version: 0.1.2
Summary: Neuromeka stereo inference utilities (TensorRT)
License: Proprietary
Keywords: stereo,tensorrt,realsense
Classifier: Programming Language :: Python :: 3
Classifier: Operating System :: OS Independent
Requires-Python: >=3.9
Requires-Dist: numpy
Provides-Extra: demo
Requires-Dist: opencv-python; extra == "demo"
Requires-Dist: pyrealsense2; extra == "demo"
